odoo/addons/maintenance_request_employee/README.rst
odoo/addons/maintenance_request_employee/__init__.py
odoo/addons/maintenance_request_employee/__manifest__.py
odoo/addons/maintenance_request_employee/i18n/es.po
odoo/addons/maintenance_request_employee/i18n/it.po
odoo/addons/maintenance_request_employee/i18n/maintenance_request_employee.pot
odoo/addons/maintenance_request_employee/models/__init__.py
odoo/addons/maintenance_request_employee/models/maintenance_request.py
odoo/addons/maintenance_request_employee/readme/CONTRIBUTORS.md
odoo/addons/maintenance_request_employee/readme/DESCRIPTION.md
odoo/addons/maintenance_request_employee/static/description/icon.png
odoo/addons/maintenance_request_employee/static/description/icon.svg
odoo/addons/maintenance_request_employee/static/description/index.html
odoo/addons/maintenance_request_employee/tests/__init__.py
odoo/addons/maintenance_request_employee/tests/test_maintenance_request_employee.py
odoo/addons/maintenance_request_employee/views/maintenance_request_views.xml
odoo_addon_maintenance_request_employee-18.0.1.0.0.2.dist-info/METADATA
odoo_addon_maintenance_request_employee-18.0.1.0.0.2.dist-info/WHEEL
odoo_addon_maintenance_request_employee-18.0.1.0.0.2.dist-info/top_level.txt
odoo_addon_maintenance_request_employee-18.0.1.0.0.2.dist-info/RECORD
